hg_config_reader/__init__.py
hg_config_reader/utils/__init__.py
hg_config_reader-0.0.2.dist-info/DESCRIPTION.rst
hg_config_reader-0.0.2.dist-info/METADATA
hg_config_reader-0.0.2.dist-info/RECORD
hg_config_reader-0.0.2.dist-info/WHEEL
hg_config_reader-0.0.2.dist-info/metadata.json
hg_config_reader-0.0.2.dist-info/top_level.txt
