Metadata-Version: 2.0
Name: hg-config-reader
Version: 0.0.2
Summary: 一个用于 huoguan.net 下各项目的简单的配置文件读取工具（项目已重命名为 simple-config-reader）
Home-page: https://github.com/anjianshi/hg-config-reader
Author: anjianshi
Author-email: anjianshi@gmail.com
License: MIT
Keywords: yaml,config
Platform: any
Classifier: Intended Audience :: Developers
Classifier: License :: OSI Approved :: MIT License
Classifier: Operating System :: OS Independent
Classifier: Programming Language :: Python
Classifier: Programming Language :: Python :: 3
Classifier: Programming Language :: Python :: 3.5
Classifier: Programming Language :: Python :: 3.6
Requires-Dist: PyYAML
